README.md
setup.py
topic_suggestor/__init__.py
topic_suggestor/base.py
topic_suggestor/bing.py
topic_suggestor/google.py
topic_suggestor/thesaurus.py
topic_suggestor.egg-info/PKG-INFO
topic_suggestor.egg-info/SOURCES.txt
topic_suggestor.egg-info/dependency_links.txt
topic_suggestor.egg-info/requires.txt
topic_suggestor.egg-info/top_level.txt